huaweicloudsdkcc/__init__.py
huaweicloudsdkcc/v2/__init__.py
huaweicloudsdkcc/v2/cc_async_client.py
huaweicloudsdkcc/v2/cc_client.py
huaweicloudsdkcc/v2/model/__init__.py
huaweicloudsdkcc/v2/model/agg_tag.py
huaweicloudsdkcc/v2/model/batch_create_delete_tags_request.py
huaweicloudsdkcc/v2/model/batch_create_delete_tags_response.py
huaweicloudsdkcc/v2/model/create_tag_request.py
huaweicloudsdkcc/v2/model/create_tag_request_body.py
huaweicloudsdkcc/v2/model/create_tag_response.py
huaweicloudsdkcc/v2/model/delete_tag_request.py
huaweicloudsdkcc/v2/model/delete_tag_response.py
huaweicloudsdkcc/v2/model/filter_tag_resource.py
huaweicloudsdkcc/v2/model/list_domain_tags_request.py
huaweicloudsdkcc/v2/model/list_domain_tags_response.py
huaweicloudsdkcc/v2/model/list_resource_by_filter_tag_request.py
huaweicloudsdkcc/v2/model/list_resource_by_filter_tag_request_body.py
huaweicloudsdkcc/v2/model/list_resource_by_filter_tag_response.py
huaweicloudsdkcc/v2/model/list_tags_request.py
huaweicloudsdkcc/v2/model/list_tags_response.py
huaweicloudsdkcc/v2/model/resource_tags.py
huaweicloudsdkcc/v2/model/tag.py
huaweicloudsdkcc/v2/region/__init__.py
huaweicloudsdkcc/v2/region/cc_region.py
huaweicloudsdkcc/v3/__init__.py
huaweicloudsdkcc/v3/cc_async_client.py
huaweicloudsdkcc/v3/cc_client.py
huaweicloudsdkcc/v3/model/__init__.py
huaweicloudsdkcc/v3/model/apply_central_network_policy_request.py
huaweicloudsdkcc/v3/model/apply_central_network_policy_response.py
huaweicloudsdkcc/v3/model/apply_policy_id.py
huaweicloudsdkcc/v3/model/approved_state_enum.py
huaweicloudsdkcc/v3/model/area.py
huaweicloudsdkcc/v3/model/area_bandwidth_package_specification.py
huaweicloudsdkcc/v3/model/area_id.py
huaweicloudsdkcc/v3/model/area_id_def.py
huaweicloudsdkcc/v3/model/asn.py
huaweicloudsdkcc/v3/model/associate_bandwidth_package.py
huaweicloudsdkcc/v3/model/associate_bandwidth_package_request.py
huaweicloudsdkcc/v3/model/associate_bandwidth_package_request_body.py
huaweicloudsdkcc-3.1.184.dist-info/METADATA
huaweicloudsdkcc-3.1.184.dist-info/WHEEL
huaweicloudsdkcc-3.1.184.dist-info/licenses/LICENSE
huaweicloudsdkcc-3.1.184.dist-info/RECORD
